pyhipp/__init__.py
pyhipp/astro/__init__.py
pyhipp/astro/coords/__init__.py
pyhipp/astro/coords/cvt.py
pyhipp/astro/cosmology/__init__.py
pyhipp/astro/cosmology/flat_lambda_cdm_nr.py
pyhipp/astro/cosmology/halo_theory.py
pyhipp/astro/cosmology/model.py
pyhipp/astro/cosmology/param.py
pyhipp/astro/cosmology/power_spectrum.py
pyhipp/astro/data/cosmologies/_737.json
pyhipp/astro/data/cosmologies/eagle.json
pyhipp/astro/data/cosmologies/elucid.json
pyhipp/astro/data/cosmologies/elucid_wmap9.json
pyhipp/astro/data/cosmologies/millennium.json
pyhipp/astro/data/cosmologies/millennium_wmap7.json
pyhipp/astro/data/cosmologies/tng.json
pyhipp/astro/data/cosmologies/eagle/data.hdf5
pyhipp/astro/data/cosmologies/elucid/data.hdf5
pyhipp/astro/data/cosmologies/simba/data.hdf5
pyhipp/astro/data/cosmologies/tng/data.hdf5
pyhipp/astro/plot/__init__.py
pyhipp/astro/plot/shortcuts.py
pyhipp/astro/quantity/__init__.py
pyhipp/astro/quantity/unit_system.py
pyhipp/astro/stats/__init__.py
pyhipp/astro/stats/lss.py
pyhipp/core/__init__.py
pyhipp/core/abc.py
pyhipp/core/arrays/__init__.py
pyhipp/core/arrays/array.py
pyhipp/core/arrays/dtype.py
pyhipp/core/containers/__init__.py
pyhipp/core/containers/data_dict.py
pyhipp/core/containers/data_table.py
pyhipp/core/dataproc/__init__.py
pyhipp/core/dataproc/data_structs.py
pyhipp/core/dataproc/filter.py
pyhipp/core/dataproc/frame.py
pyhipp/core/dataproc/grid.py
pyhipp/core/dataproc/iter.py
pyhipp/core/dataproc/mask.py
pyhipp/core/dataproc/num.py
pyhipp/field/__init__.py
pyhipp/field/cubic_box/__init__.py
pyhipp/field/cubic_box/cosmic_web.py
pyhipp/field/cubic_box/fft.py
pyhipp/field/cubic_box/field.py
pyhipp/field/cubic_box/gravity.py
pyhipp/field/cubic_box/mass_assignment.py
pyhipp/field/cubic_box/mesh.py
pyhipp/field/cubic_box/smoothing.py
pyhipp/field/neighbor/__init__.py
pyhipp/field/neighbor/kd_mesh.py
pyhipp/field/neighbor/kd_tree.py
pyhipp/group_theory/point_group.py
pyhipp/io/__init__.py
pyhipp/io/yaml.py
pyhipp/io/binary/fortran.py
pyhipp-0.3.5.dist-info/licenses/LICENSE
pyhipp-0.3.5.dist-info/METADATA
pyhipp-0.3.5.dist-info/WHEEL
pyhipp-0.3.5.dist-info/top_level.txt
pyhipp-0.3.5.dist-info/RECORD
