Metadata-Version: 2.4
Name: pyhipp
Version: 0.3.5
Summary: Modern Python toolkit for HPC
Author-email: Yangyao Chen <yangyaochen.astro@foxmail.com>
Project-URL: Repository, https://github.com/ChenYangyao/pyhipp.git
Classifier: Programming Language :: Python :: 3
Classifier: License :: OSI Approved :: MIT License
Classifier: Operating System :: OS Independent
Requires-Python: >=3.11
License-File: LICENSE
Requires-Dist: numpy
Requires-Dist: h5py
Requires-Dist: scipy
Requires-Dist: astropy
Requires-Dist: pyyaml
Requires-Dist: matplotlib
Requires-Dist: numba
Requires-Dist: scikit-learn
Requires-Dist: pandas
Requires-Dist: pytest>=7.0.0
Requires-Dist: importlib_resources
Requires-Dist: flake8
Dynamic: license-file
